Workbook

Sheet RevenueTbl
B2: Trans-id | C2: Date | D2: Client_id | E2: Client | F2: First Name | G2: Last Name | H2: Dept_id | I2: Department | J2: State_id | K2: State | L2: Payment_id | M2: Payment | N2: Revenue | O2: Profit | P2: Profit Margin
B3: TR-101 | C3: 45076 | D3: =VLOOKUP(E3:E30,ClientTbl!B$3:C$30,2,TRUE) -> C-100 | E3: AMAZON.COM, INC. | F3: Bill | G3: Smith | H3: =VLOOKUP(I3:I30,DeparmentTbl!B$3:C$6,2,TRUE) -> 102 | I3: Cloud Tech | J3: =VLOOKUP(K3:K30,StateTbl!B$3:C$6,2,TRUE) -> 104 | K3: Texas | L3: =VLOOKUP(M3:M30,PaymentTbl!B$3:C$7,2,TRUE) -> 105 | M3: Transfer | N3: 4500 | O3: 598 | P3: 0.13
B4: TR-102 | C4: 45076 | D4: =VLOOKUP(E4:E31,ClientTbl!B$3:C$30,2,TRUE) -> C-122 | E4: TESLA, INC. | F4: Ken | G4: Singh | H4: =VLOOKUP(I4:I31,DeparmentTbl!B$3:C$6,2,TRUE) -> 104 | I4: Strategy | J4: =VLOOKUP(K4:K31,StateTbl!B$3:C$6,2,TRUE) -> 103 | K4: New York | L4: =VLOOKUP(M4:M31,PaymentTbl!B$3:C$7,2,TRUE) -> 104 | M4: PayPal | N4: 3800 | O4: 1045 | P4: =O4/N4 -> 0.275
B5: TR-103 | C5: 45076 | D5: =VLOOKUP(E5:E32,ClientTbl!B$3:C$30,2,TRUE) -> C-120 | E5: NETFLIX, INC. | F5: Harley | G5: Fritz | H5: =VLOOKUP(I5:I32,DeparmentTbl!B$3:C$6,2,TRUE) -> 104 | I5: Strategy | J5: =VLOOKUP(K5:K32,StateTbl!B$3:C$6,2,TRUE) -> 103 | K5: New York | L5: =VLOOKUP(M5:M32,PaymentTbl!B$3:C$7,2,TRUE) -> 103 | M5: Others | N5: 3712.5 | O5: 1009 | P5: =O5/N5 -> 0.27178451
B6: TR-104 | C6: 45076 | D6: =VLOOKUP(E6:E33,ClientTbl!B$3:C$30,2,TRUE) -> C-125 | E6: THE PROCTER & GAMBLE COMPANY | F6: Nyla | G6: Novak | H6: =VLOOKUP(I6:I33,DeparmentTbl!B$3:C$6,2,TRUE) -> 103 | I6: Operations | J6: =VLOOKUP(K6:K33,StateTbl!B$3:C$6,2,TRUE) -> 102 | K6: Florida | L6: =VLOOKUP(M6:M33,PaymentTbl!B$3:C$7,2,TRUE) -> 103 | M6: Others | N6: 4994.2241 | O6: 779 | P6: 0.16
B7: TR-105 | C7: 45076 | D7: =VLOOKUP(E7:E34,ClientTbl!B$3:C$30,2,TRUE) -> C-123 | E7: THE GOLDMAN SACHS GROUP, INC. | F7: David | G7: Rasmussen | H7: =VLOOKUP(I7:I34,DeparmentTbl!B$3:C$6,2,TRUE) -> 103 | I7: Operations | J7: =VLOOKUP(K7:K34,StateTbl!B$3:C$6,2,TRUE) -> 102 | K7: Florida | L7: =VLOOKUP(M7:M34,PaymentTbl!B$3:C$7,2,TRUE) -> 102 | M7: Check | N7: 5000 | O7: 684 | P7: =O7/N7 -> 0.1368
B8: TR-106 | C8: 45077 | D8: =VLOOKUP(E8:E35,ClientTbl!B$3:C$30,2,TRUE) -> C-115 | E8: JPMORGAN CHASE & CO. | F8: Ivan | G8: Hiney | H8: =VLOOKUP(I8:I35,DeparmentTbl!B$3:C$6,2,TRUE) -> 102 | I8: Cloud Tech | J8: =VLOOKUP(K8:K35,StateTbl!B$3:C$6,2,TRUE) -> 104 | K8: Texas | L8: =VLOOKUP(M8:M35,PaymentTbl!B$3:C$7,2,TRUE) -> 105 | M8: Transfer | N8: 6100 | O8: 544 | P8: =O8/N8 -> 0.089180328
B9: TR-107 | C9: 45077 | D9: =VLOOKUP(E9:E36,ClientTbl!B$3:C$30,2,TRUE) -> C-119 | E9: MORGAN STANLEY | F9: Jonha | G9: Ma | H9: =VLOOKUP(I9:I36,DeparmentTbl!B$3:C$6,2,TRUE) -> 102 | I9: Cloud Tech | J9: =VLOOKUP(K9:K36,StateTbl!B$3:C$6,2,TRUE) -> 104 | K9: Texas | L9: =VLOOKUP(M9:M36,PaymentTbl!B$3:C$7,2,TRUE) -> 105 | M9: Transfer | N9: 4625 | O9: 670 | P9: =O9/N9 -> 0.14486486
B10: TR-108 | C10: 45077 | D10: =VLOOKUP(E10:E37,ClientTbl!B$3:C$30,2,TRUE) -> C-105 | E10: CITIGROUP INC. | F10: Jordan | G10: Boone | H10: =VLOOKUP(I10:I37,DeparmentTbl!B$3:C$6,2,TRUE) -> 102 | I10: Cloud Tech | J10: =VLOOKUP(K10:K37,StateTbl!B$3:C$6,2,TRUE) -> 104 | K10: Texas | L10: =VLOOKUP(M10:M37,PaymentTbl!B$3:C$7,2,TRUE) -> 105 | M10: Transfer | N10: 3800 | O10: 2045 | P10: =O10/N10 -> 0.53815789
B11: TR-109 | C11: 45077 | D11: =VLOOKUP(E11:E38,ClientTbl!B$3:C$30,2,TRUE) -> C-102 | E11: BANK OF AMERICA CORPORATION | F11: Kylee | G11: Townsend | H11: =VLOOKUP(I11:I38,DeparmentTbl!B$3:C$6,2,TRUE) -> 102 | I11: Cloud Tech | J11: =VLOOKUP(K11:K38,StateTbl!B$3:C$6,2,TRUE) -> 104 | K11: Texas | L11: =VLOOKUP(M11:M38,PaymentTbl!B$3:C$7,2,TRUE) -> 101 | M11: Card | N11: 3600 | O11: 1564 | P11: =O11/N11 -> 0.43444444
B12: TR-110 | C12: 45077 | D12: =VLOOKUP(E12:E39,ClientTbl!B$3:C$30,2,TRUE) -> C-127 | E12: WALMART INC. | F12: Nora | G12: Rollins | H12: =VLOOKUP(I12:I39,DeparmentTbl!B$3:C$6,2,TRUE) -> 102 | I12: Cloud Tech | J12: =VLOOKUP(K12:K39,StateTbl!B$3:C$6,2,TRUE) -> 104 | K12: Texas | L12: =VLOOKUP(M12:M39,PaymentTbl!B$3:C$7,2,TRUE) -> 102 | M12: Check | N12: 5100 | O12: 1220 | P12: =O12/N12 -> 0.23921569
B13: TR-111 | C13: 45077 | D13: =VLOOKUP(E13:E40,ClientTbl!B$3:C$30,2,TRUE) -> C-121 | E13: TARGET CORPORATION | F13: Brendan | G13: Wallace | H13: =VLOOKUP(I13:I40,DeparmentTbl!B$3:C$6,2,TRUE) -> 102 | I13: Cloud Tech | J13: =VLOOKUP(K13:K40,StateTbl!B$3:C$6,2,TRUE) -> 104 | K13: Texas | L13: =VLOOKUP(M13:M40,PaymentTbl!B$3:C$7,2,TRUE) -> 102 | M13: Check | N13: 4750 | O13: 1435 | P13: =O13/N13 -> 0.30210526
B14: TR-112 | C14: 45077 | D14: =VLOOKUP(E14:E41,ClientTbl!B$3:C$30,2,TRUE) -> C-107 | E14: COSTCO WHOLESALE CORPORATION | F14: Conor | G14: Wise | H14: =VLOOKUP(I14:I41,DeparmentTbl!B$3:C$6,2,TRUE) -> 103 | I14: Operations | J14: =VLOOKUP(K14:K41,StateTbl!B$3:C$6,2,TRUE) -> 102 | K14: Florida | L14: =VLOOKUP(M14:M41,PaymentTbl!B$3:C$7,2,TRUE) -> 105 | M14: Transfer | N14: 6000 | O14: 998 | P14: =O14/N14 -> 0.16633333
B15: TR-113 | C15: 45077 | D15: =VLOOKUP(E15:E42,ClientTbl!B$3:C$30,2,TRUE) -> C-117 | E15: MCDONALD'S CORPORATION | F15: Steven | G15: Michael | H15: =VLOOKUP(I15:I42,DeparmentTbl!B$3:C$6,2,TRUE) -> 101 | I15: Big Data | J15: =VLOOKUP(K15:K42,StateTbl!B$3:C$6,2,TRUE) -> 101 | K15: California | L15: =VLOOKUP(M15:M42,PaymentTbl!B$3:C$7,2,TRUE) -> 102 | M15: Check | N15: 4500 | O15: 780 | P15: =O15/N15 -> 0.17333333
B16: TR-114 | C16: 45078 | D16: =VLOOKUP(E16:E43,ClientTbl!B$3:C$30,2,TRUE) -> C-109 | E16: EXXON MOBIL CORPORATION | F16: Lucia | G16: Mckay | H16: =VLOOKUP(I16:I43,DeparmentTbl!B$3:C$6,2,TRUE) -> 101 | I16: Big Data | J16: =VLOOKUP(K16:K43,StateTbl!B$3:C$6,2,TRUE) -> 101 | K16: California | L16: =VLOOKUP(M16:M43,PaymentTbl!B$3:C$7,2,TRUE) -> 101 | M16: Card | N16: 4994.2241 | O16: 1044 | P16: =IFERROR(O16/N16,0) -> 0.20904148
B17: TR-115 | C17: 45078 | D17: =VLOOKUP(E17:E44,ClientTbl!B$3:C$30,2,TRUE) -> C-126 | E17: VERIZON COMMUNICATIONS INC. | F17: Jose | G17: Roach | H17: =VLOOKUP(I17:I44,DeparmentTbl!B$3:C$6,2,TRUE) -> 101 | I17: Big Data | J17: =VLOOKUP(K17:K44,StateTbl!B$3:C$6,2,TRUE) -> 101 | K17: California | L17: =VLOOKUP(M17:M44,PaymentTbl!B$3:C$7,2,TRUE) -> 105 | M17: Transfer | N17: 3712.5 | O17: 1222 | P17: =O17/N17 -> 0.32915825
B18: TR-116 | C18: 45078 | D18: =VLOOKUP(E18:E45,ClientTbl!B$3:C$30,2,TRUE) -> C-124 | E18: THE HOME DEPOT, INC. | F18: Franklin | G18: Wrigt | H18: =VLOOKUP(I18:I45,DeparmentTbl!B$3:C$6,2,TRUE) -> 101 | I18: Big Data | J18: =VLOOKUP(K18:K45,StateTbl!B$3:C$6,2,TRUE) -> 101 | K18: California | L18: =VLOOKUP(M18:M45,PaymentTbl!B$3:C$7,2,TRUE) -> 105 | M18: Transfer | N18: 4950 | O18: 1065 | P18: =O18/N18 -> 0.21515152
B19: TR-117 | C19: 45078 | D19: =VLOOKUP(E19:E46,ClientTbl!B$3:C$30,2,TRUE) -> C-104 | E19: CISCO SYSTEMS, INC. | F19: Alia | G19: Thornton | H19: =VLOOKUP(I19:I46,DeparmentTbl!B$3:C$6,2,TRUE) -> 103 | I19: Operations | J19: =VLOOKUP(K19:K46,StateTbl!B$3:C$6,2,TRUE) -> 102 | K19: Florida | L19: =VLOOKUP(M19:M46,PaymentTbl!B$3:C$7,2,TRUE) -> 105 | M19: Transfer | N19: 4750 | O19: 810 | P19: =O19/N19 -> 0.17052632
B20: TR-118 | C20: 45078 | D20: =VLOOKUP(E20:E47,ClientTbl!B$3:C$30,2,TRUE) -> C-103 | E20: CHEVRON CORPORATION | F20: Denzel | G20: Flores | H20: =VLOOKUP(I20:I47,DeparmentTbl!B$3:C$6,2,TRUE) -> 103 | I20: Operations | J20: =VLOOKUP(K20:K47,StateTbl!B$3:C$6,2,TRUE) -> 102 | K20: Florida | L20: =VLOOKUP(M20:M47,PaymentTbl!B$3:C$7,2,TRUE) -> 105 | M20: Transfer | N20: 7320 | O20: 933 | P20: =O20/N20 -> 0.12745902
B21: TR-119 | C21: 45078 | D21: =VLOOKUP(E21:E48,ClientTbl!B$3:C$30,2,TRUE) -> C-101 | E21: AT&T INC. | F21: Bruno | G21: Cordova | H21: =VLOOKUP(I21:I48,DeparmentTbl!B$3:C$6,2,TRUE) -> 101 | I21: Big Data | J21: =VLOOKUP(K21:K48,StateTbl!B$3:C$6,2,TRUE) -> 101 | K21: California | L21: =VLOOKUP(M21:M48,PaymentTbl!B$3:C$7,2,TRUE) -> 105 | M21: Transfer | N21: 5087.5 | O21: 655 | P21: =O21/N21 -> 0.12874693
B22: TR-120 | C22: 45078 | D22: =VLOOKUP(E22:E49,ClientTbl!B$3:C$30,2,TRUE) -> C-113 | E22: INTEL CORPORATION | F22: Jaylynn | G22: Napp | H22: =VLOOKUP(I22:I49,DeparmentTbl!B$3:C$6,2,TRUE) -> 101 | I22: Big Data | J22: =VLOOKUP(K22:K49,StateTbl!B$3:C$6,2,TRUE) -> 101 | K22: California | L22: =VLOOKUP(M22:M49,PaymentTbl!B$3:C$7,2,TRUE) -> 105 | M22: Transfer | N22: 4500 | O22: 722 | P22: =O22/N22 -> 0.16044444
B23: TR-121 | C23: 45078 | D23: =VLOOKUP(E23:E50,ClientTbl!B$3:C$30,2,TRUE) -> C-112 | E23: GENERAL MOTORS COMPANY | F23: Bruce | G23: Rich | H23: =VLOOKUP(I23:I50,DeparmentTbl!B$3:C$6,2,TRUE) -> 101 | I23: Big Data | J23: =VLOOKUP(K23:K50,StateTbl!B$3:C$6,2,TRUE) -> 101 | K23: California | L23: =VLOOKUP(M23:M50,PaymentTbl!B$3:C$7,2,TRUE) -> 101 | M23: Card | N23: 4250 | O23: 901 | P23: =O23/N23 -> 0.212
B24: TR-122 | C24: 45079 | D24: =VLOOKUP(E24:E51,ClientTbl!B$3:C$30,2,TRUE) -> C-118 | E24: MICROSOFT CORPORATION | F24: Arturo | G24: Moore | H24: =VLOOKUP(I24:I51,DeparmentTbl!B$3:C$6,2,TRUE) -> 101 | I24: Big Data | J24: =VLOOKUP(K24:K51,StateTbl!B$3:C$6,2,TRUE) -> 101 | K24: California | L24: =VLOOKUP(M24:M51,PaymentTbl!B$3:C$7,2,TRUE) -> 104 | M24: PayPal | N24: 5250 | O24: 1349 | P24: =O24/N24 -> 0.25695238
B25: TR-123 | C25: 45079 | D25: =VLOOKUP(E25:E52,ClientTbl!B$3:C$30,2,TRUE) -> C-106 | E25: COMCAST CORPORATION | F25: Bryce | G25: Carpenter | H25: =VLOOKUP(I25:I52,DeparmentTbl!B$3:C$6,2,TRUE) -> 104 | I25: Strategy | J25: =VLOOKUP(K25:K52,StateTbl!B$3:C$6,2,TRUE) -> 103 | K25: New York | L25: =VLOOKUP(M25:M52,PaymentTbl!B$3:C$7,2,TRUE) -> 104 | M25: PayPal | N25: 6500 | O25: 1288 | P25: =O25/N25 -> 0.19815385
B26: TR-124 | C26: 45079 | D26: =VLOOKUP(E26:E53,ClientTbl!B$3:C$30,2,TRUE) -> C-108 | E26: DELL TECHNOLOGIES INC. | F26: Jaidyn | G26: Andersen | H26: =VLOOKUP(I26:I53,DeparmentTbl!B$3:C$6,2,TRUE) -> 104 | I26: Strategy | J26: =VLOOKUP(K26:K53,StateTbl!B$3:C$6,2,TRUE) -> 103 | K26: New York | L26: =VLOOKUP(M26:M53,PaymentTbl!B$3:C$7,2,TRUE) -> 104 | M26: PayPal | N26: 7500 | O26: 1664 | P26: =O26/N26 -> 0.22186667
B27: TR-125 | C27: 45079 | D27: =VLOOKUP(E27:E54,ClientTbl!B$3:C$30,2,TRUE) -> C-114 | E27: JOHNSON & JOHNSON | F27: Mark | G27: Walm | H27: =VLOOKUP(I27:I54,DeparmentTbl!B$3:C$6,2,TRUE) -> 104 | I27: Strategy | J27: =VLOOKUP(K27:K54,StateTbl!B$3:C$6,2,TRUE) -> 103 | K27: New York | L27: =VLOOKUP(M27:M54,PaymentTbl!B$3:C$7,2,TRUE) -> 105 | M27: Transfer | N27: 5500 | O27: 1320 | P27: =O27/N27 -> 0.24
B28: TR-126 | C28: 45079 | D28: =VLOOKUP(E28:E55,ClientTbl!B$3:C$30,2,TRUE) -> C-110 | E28: FEDEX CORPORATION | F28: Harry | G28: Lee | H28: =VLOOKUP(I28:I55,DeparmentTbl!B$3:C$6,2,TRUE) -> 104 | I28: Strategy | J28: =VLOOKUP(K28:K55,StateTbl!B$3:C$6,2,TRUE) -> 103 | K28: New York | L28: =VLOOKUP(M28:M55,PaymentTbl!B$3:C$7,2,TRUE) -> 105 | M28: Transfer | N28: 4625 | O28: 1001 | P28: =O28/N28 -> 0.21643243
... B30: TR-128 | C30: 45079 | D30: =VLOOKUP(E30:E57,ClientTbl!B$3:C$30,2,TRUE) -> C-116 | E30: LOCKHEED MARTIN CORPORATION | F30: Mik | G30: Naam | H30: =VLOOKUP(I30:I57,DeparmentTbl!B$3:C$6,2,TRUE) -> 104 | I30: Strategy | J30: =VLOOKUP(K30:K57,StateTbl!B$3:C$6,2,TRUE) -> 103 | K30: New York | L30: =VLOOKUP(M30:M57,PaymentTbl!B$3:C$7,2,TRUE) -> 101 | M30: Card | N30: 5400 | O30: 540 | P30: =O30/N30 -> 0.1
N34: =AVERAGE(N3:N33) -> 4975.7482

Sheet StateTbl
B2: State | C2: State_id
B3: California | C3: 101
B4: Florida | C4: 102
B5: New York | C5: 103
B6: Texas | C6: 104

Sheet PaymentTbl
B2: Payment | C2: Paymen_id
B3: Card | C3: 101
B4: Check | C4: 102
B5: Others | C5: 103
B6: PayPal | C6: 104
B7: Transfer | C7: 105

Sheet DeparmentTbl
B2: Department | C2: Dept_id
B3: Big Data | C3: 101
B4: Cloud Tech | C4: 102
B5: Operations | C5: 103
B6: Strategy | C6: 104

Sheet ClientTbl
B2: Client | C2: Client_id | D2: First Name | E2: Last Name
B3: AMAZON.COM, INC. | C3: C-100 | D3: Bill | E3: Smith
B4: AT&T INC. | C4: C-101 | D4: Bruno | E4: Cordova
B5: BANK OF AMERICA CORPORATION | C5: C-102 | D5: Kylee | E5: Townsend
B6: CHEVRON CORPORATION | C6: C-103 | D6: Denzel | E6: Flores
B7: CISCO SYSTEMS, INC. | C7: C-104 | D7: Alia | E7: Thornton
B8: CITIGROUP INC. | C8: C-105 | D8: Jordan | E8: Boone
B9: COMCAST CORPORATION | C9: C-106 | D9: Bryce | E9: Carpenter
B10: COSTCO WHOLESALE CORPORATION | C10: C-107 | D10: Conor | E10: Wise
B11: DELL TECHNOLOGIES INC. | C11: C-108 | D11: Jaidyn | E11: Andersen
B12: EXXON MOBIL CORPORATION | C12: C-109 | D12: Lucia | E12: Mckay
B13: FEDEX CORPORATION | C13: C-110 | D13: Harry | E13: Lee
... B30: WALMART INC. | C30: C-127 | D30: Nora | E30: Rollins

Sheet Dirty Data
B2: Date | C2: Client | D2: Contact | E2: Department | F2: Payment | G2: Revenue | H2: Profit | I2: Profit Margin
B3: 45076 | C3: AMAZON.COM, INC. (XNAS:AMZN) | D3: Bill SmITH | E3: Cloud Tech_Texas | F3: Transfer | G3: 4500 | H3: 598 | I3: =H3/G3 -> 0.13288889
B4: 45076 | C4: TESLA, INC. (XNAS:TSLA) | D4: KEN Singh | E4: Strategy_New York | F4: PayPal | G4: 3800 | H4: 1045 | I4: =H4/G4 -> 0.275
B5: 45076 | C5: NETFLIX, INC. (XNAS:NFLX) | D5: Harley Fritz | E5: Strategy_New York | G5: 3712.5 | H5: 1009 | I5: =H5/G5 -> 0.27178451
B6: 45076 | C6: THE PROCTER & GAMBLE COMPANY (XNYS:PG) | D6: Nyla Novak | E6: Operations_Florida | H6: 779 | I6: =H6/G6 -> #DIV/0!
B7: 45076 | C7: THE GOLDMAN SACHS GROUP, INC. (XNYS:GS) | D7: David Rasmussen | E7: Operations_Florida | F7: Check | G7: 5000 | H7: 684 | I7: =H7/G7 -> 0.1368
B8: 45077 | C8: JPMORGAN CHASE & CO. (XNYS:JPM) | D8: IVAN HINEY | E8: Cloud Tech_Texas | F8: Transfer | G8: 6100 | H8: 544 | I8: =H8/G8 -> 0.089180328
B9: 45077 | C9: MORGAN STANLEY (XNYS:MS) | D9: JONha Ma | E9: Cloud Tech_Texas | F9: Transfer | G9: 4625 | H9: 670 | I9: =H9/G9 -> 0.14486486
B10: 45077 | C10: CITIGROUP INC. (XNYS:C) | D10: Jordan Boone | E10: Cloud Tech_Texas | F10: Transfer | G10: 3800 | H10: 2045 | I10: =H10/G10 -> 0.53815789
B11: 45077 | C11: BANK OF AMERICA CORPORATION (XNYS:BAC) | D11: Kylee Townsend | E11: Cloud Tech_Texas | F11: Card | G11: 3600 | H11: 1564 | I11: =H11/G11 -> 0.43444444
B12: 45077 | C12: WALMART INC. (XNYS:WMT) | D12: Nora Rollins | E12: Cloud Tech_Texas | F12: Check | G12: 5100 | H12: 1220 | I12: =H12/G12 -> 0.23921569
B13: 45077 | C13: TARGET CORPORATION (XNYS:TGT) | D13: BRENDAN Wallace | E13: Cloud Tech_Texas | F13: Check | G13: 4750 | H13: 1435 | I13: =H13/G13 -> 0.30210526
B14: 45077 | C14: COSTCO WHOLESALE CORPORATION (XNAS:COST) | D14: Conor Wise | E14: Operations_Florida | F14: Transfer | G14: 6000 | H14: 998 | I14: =H14/G14 -> 0.16633333
B15: 45077 | C15: MCDONALD'S CORPORATION (XNYS:MCD) | D15: Steven MIChael | E15: Big Data_California | F15: Check | G15: 4500 | H15: 780 | I15: =H15/G15 -> 0.17333333
B16: 45078 | C16: EXXON MOBIL CORPORATION (XNYS:XOM) | D16: Lucia Mckay | E16: Big Data_California | F16: Card | H16: 1044 | I16: =H16/G16 -> #DIV/0!
B17: 45078 | C17: VERIZON COMMUNICATIONS INC. (XNYS:VZ) | D17: JoSE Roach | E17: Big Data_California | F17: Transfer | G17: 3712.5 | H17: 1222 | I17: =H17/G17 -> 0.32915825
B18: 45078 | C18: THE HOME DEPOT, INC. (XNYS:HD) | D18: Franklin WRIGT | E18: Big Data_California | F18: Transfer | G18: 4950 | H18: 1065 | I18: =H18/G18 -> 0.21515152
B19: 45078 | C19: CISCO SYSTEMS, INC. (XNAS:CSCO) | D19: Alia Thornton | E19: Operations_Florida | F19: Transfer | G19: 4750 | H19: 810 | I19: =H19/G19 -> 0.17052632
B20: 45078 | C20: CHEVRON CORPORATION (XNYS:CVX) | D20: Denzel Flores | E20: Operations_Florida | F20: Transfer | G20: 7320 | H20: 933 | I20: =H20/G20 -> 0.12745902
B21: 45077 | C21: COSTCO WHOLESALE CORPORATION (XNAS:COST) | D21: Conor Wise | E21: Operations_Florida | F21: Transfer | G21: 6000 | H21: 998 | I21: =H21/G21 -> 0.16633333
B22: 45077 | C22: MCDONALD'S CORPORATION (XNYS:MCD) | D22: Steven MIChael | E22: Big Data_California | F22: Check | G22: 4500 | H22: 780 | I22: =H22/G22 -> 0.17333333
B23: 45078 | C23: AT&T INC. (XNYS:T) | D23: Bruno CordOVA | E23: Big Data_California | F23: Transfer | G23: 5087.5 | H23: 655 | I23: =H23/G23 -> 0.12874693
B24: 45078 | C24: INTEL CORPORATION (XNAS:INTC) | D24: jaylynn napp | E24: Big Data_California | F24: Transfer | G24: 4500 | H24: 722 | I24: =H24/G24 -> 0.16044444
B25: 45078 | C25: GENERAL MOTORS COMPANY (XNYS:GM) | D25: Bruce RICH | E25: Big Data_California | F25: Card | G25: 4250 | H25: 901 | I25: =H25/G25 -> 0.212
B26: 45079 | C26: MICROSOFT CORPORATION (XNAS:MSFT) | D26: Arturo Moore | E26: Big Data_California | F26: PayPal | G26: 5250 | H26: 1349 | I26: =H26/G26 -> 0.25695238
B27: 45079 | C27: COMCAST CORPORATION (XNAS:CMCSA) | D27: Bryce Carpenter | E27: Strategy_New York | F27: PayPal | G27: 6500 | H27: 1288 | I27: =H27/G27 -> 0.19815385
B28: 45079 | C28: DELL TECHNOLOGIES INC. (XNYS:DELL) | D28: Jaidyn ANDERSEN | E28: Strategy_New York | F28: PayPal | G28: 7500 | H28: 1664 | I28: =H28/G28 -> 0.22186667
... B33: 45076 | C33: THE GOLDMAN SACHS GROUP, INC. (XNYS:GS) | D33: David Rasmussen | E33: Operations_Florida | F33: Check | G33: 5000 | H33: 684 | I33: =H33/G33 -> 0.1368
